pyppl_context.py
pyppl_context-0.0.2.dist-info/entry_points.txt
pyppl_context-0.0.2.dist-info/LICENSE
pyppl_context-0.0.2.dist-info/WHEEL
pyppl_context-0.0.2.dist-info/METADATA
pyppl_context-0.0.2.dist-info/RECORD
