Metadata-Version: 2.1
Name: pyppl-context
Version: 0.0.2
Summary: Upstream and downstream process reference for PyPPL
License: MIT
Author: pwwang
Author-email: pwwang@pwwang.com
Requires-Python: >=3.6,<4.0
Classifier: License :: OSI Approved :: MIT License
Classifier: Programming Language :: Python :: 3
Classifier: Programming Language :: Python :: 3.6
Classifier: Programming Language :: Python :: 3.7
Classifier: Programming Language :: Python :: 3.8
Requires-Dist: pyppl (>=3.0.0,<4.0.0)
